degree/__init__.py
degree-0.0.2.dist-info/LICENSE
degree-0.0.2.dist-info/METADATA
degree-0.0.2.dist-info/WHEEL
degree-0.0.2.dist-info/top_level.txt
degree-0.0.2.dist-info/RECORD
